{
  "currentGoal": {
    "name": "araba",
    "target": 1000,
    "createdAt": "2025-10-05T19:03:00.000Z"
  },
  "totalSaved": 20,
  "entries": [
    {
      "id": "1",
      "date": "2025-10-05T19:03:00.000Z",
      "description": "harclik",
      "amount": 20,
      "category": "harclik"
    }
  ],
  "categories": {
    "harclik": {
      "total": 20,
      "color": "#4CAF50"
    }
  },
  "settings": {
    "currency": "TRY",
    "autoPostToPinterest": true,
    "postFrequency": "daily",
    "lastPosted": null
  }
}
